Metadata-Version: 2.1
Name: tlplib
Version: 1.0.2
Summary: k
Author: yz
Author-email: yd@qq.com
License: MIT
License-File: LICENCE.txt
